LICENSE
README.md
pysits/__init__.py
pysits/jinja.py
pysits/settings.py
pysits/backend/__init__.py
pysits/backend/functions.py
pysits/backend/loaders.py
pysits/backend/pkgs.py
pysits/conversions/__init__.py
pysits/conversions/clojure.py
pysits/conversions/common.py
pysits/conversions/decorators.py
pysits/conversions/tibble.py
pysits/conversions/tibble_arrow.py
pysits/conversions/vector.py
pysits/conversions/xarray.py
pysits/conversions/dsl/__init__.py
pysits/conversions/dsl/base.py
pysits/conversions/dsl/mask.py
pysits/conversions/dsl/tuning.py
pysits/docs/__init__.py
pysits/docs/decorators.py
pysits/docs/content/sits_get_data.md
pysits/extras/__init__.py
pysits/extras/earthdatalogin.py
pysits/extras/torch.py
pysits/models/__init__.py
pysits/models/base.py
pysits/models/frame.py
pysits/models/ml.py
pysits/models/resolver.py
pysits/models/data/__init__.py
pysits/models/data/accuracy.py
pysits/models/data/base.py
pysits/models/data/cube.py
pysits/models/data/frame.py
pysits/models/data/frame_accessor.py
pysits/models/data/matrix.py
pysits/models/data/table.py
pysits/models/data/ts.py
pysits/models/data/tuning.py
pysits/models/data/vector.py
pysits/sits/__init__.py
pysits/sits/classification.py
pysits/sits/colors.py
pysits/sits/config.py
pysits/sits/context.py
pysits/sits/cube.py
pysits/sits/data.py
pysits/sits/impute.py
pysits/sits/ml.py
pysits/sits/segment.py
pysits/sits/tiles.py
pysits/sits/ts.py
pysits/sits/tuning.py
pysits/sits/utils.py
pysits/sits/visualization.py
pysits/sits/exporters/__init__.py
pysits/sits/exporters/files.py
pysits/sits/exporters/sf.py
pysits/sits/exporters/xarray.py
pysits/templates/cube.html
pysits/templates/tuning.html
pysits/visualization/__init__.py
pysits/visualization/base.py
pysits/visualization/image.py
pysits/visualization/leaflet.py
pysits/visualization/tmap.py
pysits-1.5.4.dist-info/METADATA
pysits-1.5.4.dist-info/WHEEL
pysits-1.5.4.dist-info/licenses/LICENSE
pysits-1.5.4.dist-info/RECORD
